<annotation>
	<folder>Data</folder>
	<filename>banana_3.jpg</filename>
	<path>D:\Github\Projet Greta ia\mini projet\Moustafa\model_fruit\Data\banana_3.jpg</path>
	<source>
		<database>Unknown</database>
	</source>
	<size>
		<width>200</width>
		<height>200</height>
		<depth>3</depth>
	</size>
	<segmented>0</segmented>
	<object>
		<name>banane</name>
		<pose>Unspecified</pose>
		<truncated>0</truncated>
		<difficult>0</difficult>
		<bndbox>
			<xmin>17</xmin>
			<ymin>36</ymin>
			<xmax>181</xmax>
			<ymax>164</ymax>
		</bndbox>
	</object>
</annotation>